sftp_composer/__init__.py
sftp_composer/cli.py
sftp_composer/model.py
sftp_composer/sftp_composer.py
sftp_composer-0.0.1.dist-info/AUTHORS.rst
sftp_composer-0.0.1.dist-info/LICENSE
sftp_composer-0.0.1.dist-info/METADATA
sftp_composer-0.0.1.dist-info/WHEEL
sftp_composer-0.0.1.dist-info/entry_points.txt
sftp_composer-0.0.1.dist-info/top_level.txt
sftp_composer-0.0.1.dist-info/RECORD
