Metadata-Version: 2.1
Name: sftp-composer
Version: 0.0.1
Summary: Render Secrets for AWS SFTP integration
Home-page: https://github.com/johnpreston/sftp_composer
Author: John Preston
Author-email: john@compose-x.io
License: UNKNOWN
Keywords: sftp_composer
Platform: UNKNOWN
Classifier: Development Status :: 2 - Pre-Alpha
Classifier: Intended Audience :: Developers
Classifier: Natural Language :: English
Classifier: Programming Language :: Python :: 3
Classifier: Programming Language :: Python :: 3.7
Classifier: Programming Language :: Python :: 3.8
Classifier: Programming Language :: Python :: 3.9
Requires-Python: >=3.7
License-File: LICENSE
License-File: AUTHORS.rst
Requires-Dist: troposphere (==2.7.1)
Requires-Dist: pydantic
